{
  "notes": [
    {
      "name": "Arto Hellas",
      "number": "040-123456",
      "id": 1
    },
    {
      "name": "Ada Lovelace",
      "number": "39-44-5323523",
      "id": 2
    },
    {
      "name": "Dan Abramov",
      "number": "12-43-234345",
      "id": 3
    },
    {
      "name": "Mary Poppendieck",
      "number": "39-23-6423122",
      "id": 4
    },
    {
      "content": "Tako gomurashvili",
      "date": "2021-02-13T02:48:13.373Z",
      "important": true,
      "id": 5
    },
    {
      "content": "შოთ",
      "date": "2021-02-13T02:48:43.784Z",
      "important": true,
      "id": 6
    },
    {
      "content": "Tako gomurashvili",
      "date": "2021-02-13T02:54:09.500Z",
      "important": false,
      "id": 7
    },
    {
      "content": "ელექტროობა",
      "date": "2021-02-13T03:18:46.287Z",
      "important": true,
      "id": 8
    },
    {
      "content": "შოთ",
      "date": "2021-02-13T03:26:41.141Z",
      "important": true,
      "id": 9
    },
    {
      "content": "შოთ",
      "date": "2021-02-13T03:26:44.969Z",
      "important": false,
      "id": 10
    },
    {
      "content": "Strrhi",
      "date": "2021-02-13T03:33:29.121Z",
      "important": false,
      "id": 11
    },
    {
      "content": "fssdwd",
      "date": "2021-02-13T03:35:10.913Z",
      "important": false,
      "id": 12
    },
    {
      "content": "შოთ",
      "date": "2021-02-13T03:40:46.289Z",
      "important": false,
      "id": 13
    },
    {
      "content": "შოთ",
      "date": "2021-02-13T03:40:50.193Z",
      "important": false,
      "id": 14
    },
    {
      "content": "ererer",
      "date": "2021-05-29T17:17:11.537Z",
      "important": false,
      "id": 15
    },
    {
      "content": "ererer",
      "date": "2021-05-29T17:17:12.200Z",
      "important": false,
      "id": 16
    },
    {
      "content": "ererer1212",
      "date": "2021-05-29T17:17:23.022Z",
      "important": false,
      "id": 17
    },
    {
      "content": "ererer1212",
      "date": "2021-05-29T17:17:31.014Z",
      "important": false,
      "id": 18
    }
  ]
}